apifish/__init__.py
apifish/build_matrix/__init__.py
apifish/build_traces/__init__.py
apifish/classification/__init__.py
apifish/classification/features.py
apifish/classification/input_preparation.py
apifish/classification/tests/__init__.py
apifish/classification/tests/test_features.py
apifish/classification/tests/test_input_preparation.py
apifish/deep_learning/__init__.py
apifish/deep_learning/models_segmentation.py
apifish/deep_learning/utils_models.py
apifish/detection/__init__.py
apifish/detection/cluster_detection.py
apifish/detection/dense_decomposition.py
apifish/detection/spot_detection.py
apifish/detection/spot_modeling.py
apifish/detection/utils.py
apifish/detection/tests/__init__.py
apifish/detection/tests/test_cluster_detection.py
apifish/detection/tests/test_dense_decomposition.py
apifish/detection/tests/test_spot_detection.py
apifish/detection/tests/test_spot_modeling.py
apifish/detection/tests/test_utils.py
apifish/multistack/__init__.py
apifish/multistack/colocalization.py
apifish/multistack/postprocess.py
apifish/multistack/preprocess.py
apifish/multistack/utils.py
apifish/multistack/tests/__init__.py
apifish/multistack/tests/test_colocalization.py
apifish/multistack/tests/test_postprocess.py
apifish/multistack/tests/test_preprocess.py
apifish/multistack/tests/test_utils.py
apifish/plot/__init__.py
apifish/plot/plot_images.py
apifish/plot/plot_quality.py
apifish/plot/utils.py
apifish/registration/__init__.py
apifish/segmentation/__init__.py
apifish/segmentation/cell_segmentation.py
apifish/segmentation/nuc_segmentation.py
apifish/segmentation/postprocess.py
apifish/segmentation/utils.py
apifish/segmentation/test/__init__.py
apifish/segmentation/test/test_cell_segmentation.py
apifish/segmentation/test/test_nuc_segmentation.py
apifish/segmentation/test/test_postprocess.py
apifish/segmentation/test/test_utils.py
apifish/stack/__init__.py
apifish/stack/augmentation.py
apifish/stack/filter.py
apifish/stack/io.py
apifish/stack/preprocess.py
apifish-0.6.4.dev0.dist-info/LICENSE
apifish-0.6.4.dev0.dist-info/METADATA
apifish-0.6.4.dev0.dist-info/WHEEL
apifish-0.6.4.dev0.dist-info/top_level.txt
apifish-0.6.4.dev0.dist-info/RECORD
