Metadata-Version: 2.1
Name: apifish
Version: 0.6.4.dev0
Summary: Toolbox for the analysis of smFISH images.
Author-email: Arthur Imbert <arthur.imbert.pro@gmail.com>, Marcelo Nollmann <marcelo.nollmann@cbs.cnrs.fr>
License: GNU GENERAL PUBLIC LICENSE
Project-URL: Homepage, https://github.com/apiFISH/apiFISH
Requires-Python: >=3.6
License-File: LICENSE
Requires-Dist: astropy >=4.3.1
Requires-Dist: matplotlib >=3.0.2
Requires-Dist: numpy >=1.16.0
Requires-Dist: scikit-image >=0.14.2
Requires-Dist: scikit-learn >=0.21.0
Requires-Dist: scipy >=1.4.1
Requires-Dist: pandas >=0.24.0
Requires-Dist: mrc >=0.1.5
Requires-Dist: tensorflow >=2.3.0
Requires-Dist: tensorflow-addons >=0.12.1
